README.rst
setup.py
ucscsession/__init__.py
ucscsession/helpers.py
ucscsession/session.py
ucscsession/settings.py
ucscsession/tracks.py
ucscsession/version.py
ucscsession.egg-info/PKG-INFO
ucscsession.egg-info/SOURCES.txt
ucscsession.egg-info/dependency_links.txt
ucscsession.egg-info/requires.txt
ucscsession.egg-info/top_level.txt
ucscsession/test/__init__.py
ucscsession/test/data/__init__.py