Metadata-Version: 1.1
Name: ucscsession
Version: 0.1.1
Summary: ucscsession description
Home-page: none
Author: Ryan Dale
Author-email: dalerr@niddk.nih.gov
License: UNKNOWN
Platform: UNKNOWN
Classifier: Development Status :: 4 - Beta
